PyMemRW/__init__.py
PyMemRW/dellinject.py
PyMemRW-0.0.0.1.dist-info/METADATA
PyMemRW-0.0.0.1.dist-info/WHEEL
PyMemRW-0.0.0.1.dist-info/top_level.txt
PyMemRW-0.0.0.1.dist-info/RECORD
