Metadata-Version: 2.1
Name: PyMemRW
Version: 0.0.0.1
Summary: A library for manipulating memory in a Windows process
Home-page: https://github.com/Mahdi-hasan-shuvo/PyMemoryRW
Author: Mahdi Hasan Shuvo
Author-email: shuvobbhh@gmail.com
License: MIT
Project-URL: Homepage, https://github.com/Mahdi-hasan-shuvo/PyMemoryRW
Project-URL: Bug Reports, https://github.com/Mahdi-hasan-shuvo/PyMemoryRW/issues
Project-URL: Source, https://github.com/Mahdi-hasan-shuvo/PyMemoryRW
Keywords: memory manipulation Windows memory management process memory Windows API memory injection memory editing Windows process memory library process hacking Windows utilities memory access system programming memory tools Win32 API Python memory library process manipulation memory read/write Windows programming memory management library Python Windows API
Classifier: Programming Language :: Python :: 3
Classifier: License :: OSI Approved :: MIT License
Classifier: Operating System :: OS Independent
Requires-Python: >=3.11
